bankid6/__init__.py
bankid6/client.py
bankid6/exceptions.py
bankid6/handlers.py
bankid6/listify.py
bankid6/message.py
bankid6/certs/testCARootCert.pem
bankid6/certs/testCert.pem
bankid6/certs/testPrivateKey.pem
bankid6-1.1.1.dist-info/METADATA
bankid6-1.1.1.dist-info/WHEEL
bankid6-1.1.1.dist-info/licenses/LICENSE
bankid6-1.1.1.dist-info/RECORD
