Metadata-Version: 2.3
Name: bankid6
Version: 1.1.1
Summary:   A complete implementation of swedish BankID version 6.    Easily initiate, collect and cancel authentication orders,    show user message and handle errors.
Project-URL: Issues, https://github.com/mdamire/bankid-6/issues
Project-URL: ChangeLog, https://github.com/mdamire/bankid-6/blob/master/CHANGELOG.md
Author-email: Amir Ebrahim <md.amire02@gmail.com>
License-File: LICENSE
Classifier: License :: OSI Approved :: MIT License
Classifier: Operating System :: OS Independent
Classifier: Programming Language :: Python :: 3
Requires-Python: >=3.6
Requires-Dist: requests
